[
    {
        "model": "rraa.clasificacionesrraa",
        "pk": 1, 
        "fields": {
            "nomb_cla": "Sistema Armonizado de Designación y Codificación de Mercancías"
        }
    }, 
    {
        "model": "rraa.clasificacionesrraa", 
        "pk": 2,
        "fields": {
            "nomb_cla": "Clasificaciones por Grandes Categorías Económicas"
        }
    }, 
    {
        "model": "rraa.clasificacionesrraa",
        "pk": 3, 
        "fields": {
            "nomb_cla": "Clasificación del Consumo Individual por Finalidades"
        }
    }, 
    {
        "model": "rraa.clasificacionesrraa", 
        "pk": 4,
        "fields": {
            "nomb_cla": "Clasificación Ampliada de la Balanza de Pagos de Servicios"
        }
    }, 
    {
        "model": "rraa.clasificacionesrraa",
        "pk": 5, 
        "fields": {
            "nomb_cla": "Clasificación del Comercio Exterior según Uso o Destino Económico"
        }
    }, 
    {
        "model": "rraa.clasificacionesrraa", 
        "pk": 6,
        "fields": {
            "nomb_cla": "Clasificación Uniforme para el Comercio Internacional"
        }
    }, 
    {
        "model": "rraa.clasificacionesrraa",
        "pk": 7, 
        "fields": {
            "nomb_cla": "Clasificación Central de Productos"
        }
    }, 
    {
        "model": "rraa.clasificacionesrraa", 
        "pk": 8,
        "fields": {
            "nomb_cla": "Clasificación de las Funciones del Gobierno "
        }
    }, 
    {
        "model": "rraa.clasificacionesrraa",
        "pk": 9, 
        "fields": {
            "nomb_cla": "Clasificación Internacional Normalizada de la Educación"
        }
    }, 
    {
        "model": "rraa.clasificacionesrraa", 
        "pk": 10,
        "fields": {
            "nomb_cla": "Clasificación Internacional del Funcionamiento, la Discapacidad y la Salud"
        }
    }, 
    {
        "model": "rraa.clasificacionesrraa",
        "pk": 11, 
        "fields": {
            "nomb_cla": "Clasificación de las Finalidades de las Instituciones sin Fines de Lucro que sirven a los hogares"
        }
    }, 
    {
        "model": "rraa.clasificacionesrraa", 
        "pk": 12,
        "fields": {
            "nomb_cla": "Clasificación Internacional de los Delitos con Fines Estadísticos"
        }
    }, 
    {
        "model": "rraa.clasificacionesrraa",
        "pk": 13, 
        "fields": {
            "nomb_cla": "Clasificación Internacional de Actividades para Estadísticas de Uso del Tiempo"
        }
    }, 
    {
        "model": "rraa.clasificacionesrraa", 
        "pk": 14,
        "fields": {
            "nomb_cla": "Clasificación Internacional de Situación en el Empleo"
        }
    }, 
    {
        "model": "rraa.clasificacionesrraa",
        "pk": 15, 
        "fields": {
            "nomb_cla": "Clasificación Internacional de Enfermedades"
        }
    }, 
    {
        "model": "rraa.clasificacionesrraa", 
        "pk": 16,
        "fields": {
            "nomb_cla": "Clasificación Internacional de Intervenciones de Salud"
        }
    }, 
    {
        "model": "rraa.clasificacionesrraa",
        "pk": 17, 
        "fields": {
            "nomb_cla": "Clasificación de Actividades de Protección Ambiental"
        }
    }, 
    {
        "model": "rraa.clasificacionesrraa", 
        "pk": 18,
        "fields": {
            "nomb_cla": "División Político Administrativa de Colombia"
        }
    }, 
    {
        "model": "rraa.clasificacionesrraa",
        "pk": 19, 
        "fields": {
            "nomb_cla": "Nomenclatura de las Unidades"
        }
    }, 
    {
        "model": "rraa.clasificacionesrraa", 
        "pk": 20,
        "fields": {
            "nomb_cla": "Territoriales Estadísticas de la Comunidad Andina"
        }
    }, 
    {
        "model": "rraa.clasificacionesrraa",
        "pk": 21, 
        "fields": {
            "nomb_cla": "Clasificación Industrial Internacional Uniforme de todas las actividades económicas Adaptada para Colombia"
        }
    }, 
    {
        "model": "rraa.clasificacionesrraa", 
        "pk": 22,
        "fields": {
            "nomb_cla": "Clasificación Internacional Uniforme de Ocupaciones Adaptada para Colombia"
        }
    }, 
    {
        "model": "rraa.clasificacionesrraa",
        "pk": 23, 
        "fields": {
            "nomb_cla": "Clasificación Central de Productos Adapta para Colombia"
        }
    }, 
    {
        "model": "rraa.clasificacionesrraa", 
        "pk": 24,
        "fields": {
            "nomb_cla": "Clasificación Internacional Normalizada de la Educación Adapta para Colombia "
        }
    }
]